pyopensea/__init__.py
pyopensea/endpoint.py
pyopensea/opensea.py
pyopensea/util.py
py_opensea_sdk-1.0.4.dist-info/LICENSE
py_opensea_sdk-1.0.4.dist-info/METADATA
py_opensea_sdk-1.0.4.dist-info/WHEEL
py_opensea_sdk-1.0.4.dist-info/top_level.txt
py_opensea_sdk-1.0.4.dist-info/RECORD
