Metadata-Version: 2.1
Name: py-opensea-sdk
Version: 1.0.4
Summary: Python SDK for the Opensea API
Author: Abe
License: MIT License        
Project-URL: Homepage, https://github.com/FastestMolasses/PyOpenSea
Project-URL: Bug Tracker, https://github.com/FastestMolasses/PyOpenSea/issues
Keywords: opensea,api,sdk,python,nft,erc721
Classifier: License :: OSI Approved :: MIT License
Classifier: Operating System :: OS Independent
Classifier: Programming Language :: Python :: 3
Classifier: Programming Language :: Python :: 3.8
Classifier: Programming Language :: Python :: 3.9
Classifier: Programming Language :: Python :: 3.10
Requires-Python: >=3.8
License-File: LICENSE
Requires-Dist: requests (~=2.28.1)
